{"Week 8": {"2020-10-26": {"9:00 AM": "0", "9:00 AM Active minutes": "0", "11:00 AM": "0", "11:00 AM Active minutes": "0", "Total": "0"}, "2020-10-27": {"9:00 AM": "0", "9:00 AM Active minutes": "0", "11:00 AM": "0", "11:00 AM Active minutes": "0", "Total": "0"}, "2020-10-28": {"9:00 AM": "0", "9:00 AM Active minutes": "0", "11:00 AM": "0", "11:00 AM Active minutes": "0", "Total": "0"}, "2020-10-29": {"9:00 AM": "0", "9:00 AM Active minutes": "0", "11:00 AM": "0", "11:00 AM Active minutes": "0", "Total": "0"}, "2020-10-30": {"9:00 AM": "-", "9:00 AM Active minutes": "-", "11:00 AM": "0", "11:00 AM Active minutes": "0", "Total": "0"}}, "Week 9": {"2020-11-02": {"9:00 AM": "0", "9:00 AM Active minutes": "0", "11:00 AM": "0", "11:00 AM Active minutes": "0", "Total": "0"}, "2020-11-03": {"9:00 AM": "0", "9:00 AM Active minutes": "0", "11:00 AM": "0", "11:00 AM Active minutes": "0", "Total": "0"}, "2020-11-04": {"9:00 AM": "0", "9:00 AM Active minutes": "0", "11:00 AM": "0", "11:00 AM Active minutes": "0", "Total": "0"}, "2020-11-05": {"9:00 AM": "-", "9:00 AM Active minutes": "-", "11:00 AM": "0", "11:00 AM Active minutes": "0", "Total": "0"}, "2020-11-06": {"9:00 AM": "-", "9:00 AM Active minutes": "-", "11:00 AM": "0", "11:00 AM Active minutes": "0", "Total": "0"}}, "Week 10": {"2020-11-09": {"9:00 AM": "0", "9:00 AM Active minutes": "0", "11:00 AM": "0", "11:00 AM Active minutes": "0", "Total": "0"}, "2020-11-10": {"9:00 AM": "0", "9:00 AM Active minutes": "0", "11:00 AM": "0", "11:00 AM Active minutes": "0", "Total": "0"}, "2020-11-11": {"9:00 AM": "0", "9:00 AM Active minutes": "0", "11:00 AM": "0", "11:00 AM Active minutes": "0", "Total": "0"}, "2020-11-12": {"9:00 AM": "0", "9:00 AM Active minutes": "0", "11:00 AM": "0", "11:00 AM Active minutes": "0", "Total": "0"}, "2020-11-13": {"9:00 AM": "-", "9:00 AM Active minutes": "-", "11:00 AM": "0", "11:00 AM Active minutes": "0", "Total": "0"}}, "Week 11": {"2020-11-16": {"9:00 AM": "0", "9:00 AM Active minutes": "0", "11:00 AM": "0", "11:00 AM Active minutes": "0", "Total": "0"}, "2020-11-17": {"9:00 AM": "0", "9:00 AM Active minutes": "0", "11:00 AM": "0", "11:00 AM Active minutes": "0", "Total": "0"}, "2020-11-18": {"9:00 AM": "0", "9:00 AM Active minutes": "0", "11:00 AM": "0", "11:00 AM Active minutes": "0", "Total": "0"}, "2020-11-19": {"9:00 AM": "0", "9:00 AM Active minutes": "0", "11:00 AM": "0", "11:00 AM Active minutes": "0", "Total": "0"}, "2020-11-20": {"9:00 AM": "0", "9:00 AM Active minutes": "0", "11:00 AM": "0", "11:00 AM Active minutes": "0", "Total": "0"}}, "Week 12": {"2020-11-23": {"9:00 AM": "0", "9:00 AM Active minutes": "0", "11:00 AM": "0", "11:00 AM Active minutes": "0", "Total": "0"}, "2020-11-24": {"9:00 AM": "0", "9:00 AM Active minutes": "0", "11:00 AM": "0", "11:00 AM Active minutes": "0", "Total": "0"}, "2020-11-25": {"9:00 AM": "0", "9:00 AM Active minutes": "0", "Duration1": "0", "11:00 AM": "0", "11:00 AM Active minutes": "0", "Duration2": "0", "Total": "0"}, "2020-11-26": {"9:00 AM": "0", "9:00 AM Active minutes": "0", "Duration1": "0", "11:00 AM": "0", "11:00 AM Active minutes": "0", "Duration2": "0", "Total": "0"}, "2020-11-27": {"9:00 AM": "0", "9:00 AM Active minutes": "0", "Duration1": "0", "11:00 AM": "0", "11:00 AM Active minutes": "0", "Duration2": "0", "Total": "0"}}, "Week 13": {"2020-11-30": {"9:00 AM": "0", "9:00 AM Active minutes": "0", "Duration1": "0", "11:00 AM": "-", "11:00 AM Active minutes": "-", "Duration2": "-", "Total": "0"}, "2020-12-01": {"9:00 AM": "-", "9:00 AM Active minutes": "-", "Duration1": "-", "11:00 AM": "-", "11:00 AM Active minutes": "-", "Duration2": "-", "Total": "-"}, "2020-12-02": {"9:00 AM": "1", "9:00 AM Active minutes": "118", "Duration1": "120", "11:00 AM": "-", "11:00 AM Active minutes": "-", "Duration2": "-", "Total": "1"}, "2020-12-03": {"9:00 AM": "1", "9:00 AM Active minutes": "115", "Duration1": "120", "11:00 AM": "-", "11:00 AM Active minutes": "-", "Duration2": "-", "Total": "1"}, "2020-12-04": {"9:00 AM": "0", "9:00 AM Active minutes": "0", "Duration1": "0", "11:00 AM": "-", "11:00 AM Active minutes": "-", "Duration2": "-", "Total": "0"}}, "Week 14": {"2020-12-07": {"9:00 AM": "0", "9:00 AM Active minutes": "0", "Duration1": "0", "11:00 AM": "0", "11:00 AM Active minutes": "0", "Duration2": "0", "Total": "0"}, "2020-12-08": {"9:00 AM": "0", "9:00 AM Active minutes": "0", "Duration1": "0", "11:00 AM": "-", "11:00 AM Active minutes": "-", "Duration2": "-", "Total": "0"}, "2020-12-09": {"9:00 AM": "0", "9:00 AM Active minutes": "0", "Duration1": "0", "11:00 AM": "0", "11:00 AM Active minutes": "0", "Duration2": "0", "Total": "0"}, "2020-12-10": {"9:00 AM": "1", "9:00 AM Active minutes": "240", "Duration1": "241", "11:00 AM": "-", "11:00 AM Active minutes": "-", "Duration2": "-", "Total": "1"}, "2020-12-11": {"9:00 AM": "1", "9:00 AM Active minutes": "224", "Duration1": "225", "11:00 AM": "-", "11:00 AM Active minutes": "-", "Duration2": "-", "Total": "1"}}, "Week 15": {"2020-12-14": {"9:00 AM": "1", "9:00 AM Active minutes": "34", "Duration1": "35", "11:00 AM": "1", "11:00 AM Active minutes": "100", "Duration2": "102", "Total": "1"}, "2020-12-15": {"9:00 AM": "1", "9:00 AM Active minutes": "19", "Duration1": "19", "11:00 AM": "1", "11:00 AM Active minutes": "114", "Duration2": "116", "Total": "1"}, "2020-12-16": {"9:00 AM": "1", "9:00 AM Active minutes": "131", "Duration1": "150", "11:00 AM": "1", "11:00 AM Active minutes": "64", "Duration2": "66", "Total": "1"}, "2020-12-17": {"9:00 AM": "1", "9:00 AM Active minutes": "38", "Duration1": "38", "11:00 AM": "1", "11:00 AM Active minutes": "109", "Duration2": "110", "Total": "1"}}}